FlipFlop/FDCE.v
module FDCE (d, clock, clock_enable, clear, q);
    input d, clock, clock_enable, clear;
    output reg q;

    always @(posedge clock) begin
        if(clock_enable == 1 & clear == 0) begin
            q = d;
        end
    end

    always @(clear) begin
        if(clear == 1) begin
            q = 0;
        end
    end
    
endmodule

FlipFlop/FDCE_t.v
//`include "FDCE.v"
module FDCE_t ();
    reg input_d, input_clock_enable, input_clear, output_q, clock;

    FDCE fdce(input_d, clock, input_clock_enable, input_clear, output_q);

    task test(D, CE, CLR);
        input_d = D;
        input_clock_enable = CE;
        input_clear = CLR;
        #100;
    endtask

    initial begin
        clock = 0;
        $dumpfile("FDCE.vcd");
        $dumpvars;

        test(1, 1, 0);
        test(0, 1, 0);
        test(0, 1, 1);
        test(1, 1, 1);
        test(1, 0, 0);
        test(1, 1, 0);
        test(0, 0, 0);
        $finish;
    end

    always #25 begin
        clock = ~clock;
    end
    
endmodule

FlipFlop/FDCE.vcd
$date
	Thu Jul 15 22:06:25 2021
$end
$version
	Icarus Verilog
$end
$timescale
	1s
$end
$scope module FDCE_t $end
$var wire 1 ! output_q $end
$var reg 1 " clock $end
$var reg 1 # input_clear $end
$var reg 1 $ input_clock_enable $end
$var reg 1 % input_d $end
$scope module fdce $end
$var wire 1 # clear $end
$var wire 1 " clock $end
$var wire 1 $ clock_enable $end
$var wire 1 % d $end
$var reg 1 ! q $end
$upscope $end
$scope task test $end
$var reg 1 & CE $end
$var reg 1 ' CLR $end
$var reg 1 ( D $end
$upscope $end
$upscope $end
$enddefinitions $end
#0
$dumpvars
1(
0'
1&
1%
1$
0#
0"
x!
$end
#25
1!
1"
#50
0"
#75
1"
#100
0"
0%
0(
#125
0!
1"
#150
0"
#175
1"
#200
0"
1#
1'
#225
1"
#250
0"
#275
1"
#300
0"
1%
1(
#325
1"
#350
0"
#375
1"
#400
0"
0#
0$
0'
0&
#425
1"
#450
0"
#475
1"
#500
0"
1$
1&
#525
1!
1"
#550
0"
#575
1"
#600
0"
0$
0%
0&
0(
