MUX/MUX_2to1_1B.v
module MUX_2to1_1B (
	input a,
	input b,
	input select,
	output result);
	wire w1, w2, w3;

	not not1(w1, select);
	and and1(w2, a, w1);
	and and2(w3, select, b);
	or or1(result, w2, w3);

endmodule

MUX/MUX_2to1_1B_t.v
/*`include "MUX_2to1_1B.v"*/
module MUX_2to1_1B_t;
	reg output_result, input_a, input_b, input_select;
	

	MUX_2to1_1B M(input_a, input_b, input_select, output_result);

	task test(input a, input b, input select);
		input_a = a;
		input_b = b;
		input_select = select;
		#100;
	endtask

	initial begin
		$dumpfile("MUX_2to1_1B.vcd");
		$dumpvars;

		/*integer i = 3'b000;
		for (i = 3'b000; i <= 3'b111; i = i + 3'b001) begin
			test(i[0], i[1], i[2]);
		end*/

		test(1'b0, 1'b0, 1'b0);
		test(1'b1, 1'b0, 1'b0);
		test(1'b0, 1'b1, 1'b0);
		test(1'b1, 1'b1, 1'b0);
		test(1'b0, 1'b0, 1'b1);
		test(1'b1, 1'b0, 1'b1);
		test(1'b0, 1'b1, 1'b1);
		test(1'b1, 1'b1, 1'b1);

		$finish;
	end


endmodule

MUX/MUX_2to1_1B.vcd
$date
	Thu Jul 15 21:56:10 2021
$end
$version
	Icarus Verilog
$end
$timescale
	1s
$end
$scope module MUX_2to1_1B_t $end
$var wire 1 ! output_result $end
$var reg 1 " input_a $end
$var reg 1 # input_b $end
$var reg 1 $ input_select $end
$scope module M $end
$var wire 1 " a $end
$var wire 1 # b $end
$var wire 1 ! result $end
$var wire 1 $ select $end
$var wire 1 % w1 $end
$var wire 1 & w2 $end
$var wire 1 ' w3 $end
$upscope $end
$scope task test $end
$var reg 1 ( a $end
$var reg 1 ) b $end
$var reg 1 * select $end
$upscope $end
$upscope $end
$enddefinitions $end
#0
$dumpvars
0*
0)
0(
0'
0&
1%
0$
0#
0"
0!
$end
#100
1!
1&
1"
1(
#200
0!
0&
1#
0"
1)
0(
#300
1!
1&
1"
1(
#400
0!
0%
0&
1$
0#
0"
1*
0)
0(
#500
1"
1(
#600
1!
1'
1#
0"
1)
0(
#700
1"
1(
