Decoder/InstructionDecoder.v
module InstructionDecoder (a, ip, op, load, add, jump, jumpz, jumpnz, jumpc, jumpnc, sub, bitand);
    input [7:0] a;
    output reg ip, op, load, add, jump, jumpz, jumpnz, jumpc, jumpnc, sub, bitand;



    always @(a) begin
        ip = a[7] && !a[6] && a[5] && !a[4];
        op = a[7] && a[6] && a[5] && !a[4];
        load = !a[7] && !a[6] && !a[5] && !a[4];
        add = !a[7] && a[6] && !a[5] && !a[4];
        jump = a[7] && !a[6] && !a[5] && !a[4];
        if(a[7] && !a[6] && !a[5] && a[4]) begin
            jump_condition(a[3], a[2]);
        end
        else begin
            jumpz = 0;
            jumpnz = 0;
            jumpc = 0;
            jumpnc = 0;
        end
        sub = !a[7] && a[6] && a[5] && !a[4];
        bitand = !a[7] && !a[6] && !a[5] && a[4];
    end

    task jump_condition(a3, a2);
        jumpz = !a3 && !a2;
        jumpnz = !a3 && a2;
        jumpc = a3 && !a2;
        jumpnc = a3 && a2;
    endtask

endmodule

Decoder/CompleteInstructionDecoder.v
//`include "InstructionDecoder.v"
module CompleteInstructionDecoder (a, decode, execute, ip, op, load, add, jump, jumpz, jumpnz, jumpc, jumpnc, sub, bitand);
    input [7:0] a;
    input decode, execute;
    output ip, op, load, add, jump, jumpz, jumpnz, jumpc, jumpnc, sub, bitand;
    wire enable, wip, wop, wload, wadd, wjump, wjumpz, wjumpnz, wjumpc, wjumpnc, wsub, wbitand;

    InstructionDecoder ID(a, wip, wop, wload, wadd, wjump, wjumpz, wjumpnz, wjumpc, wjumpnc, wsub, wbitand);

    or o(enable, decode, execute);
    and a1(ip, enable, wip);
    and a2(op, enable, wop);
    and a3(load, enable, wload);
    and a4(add, enable, wadd);
    and a5(jump, enable, wjump);
    and a6(jumpz, enable, wjumpz);
    and a7(jumpnz, enable, wjumpnz);
    and a8(jumpc, enable, wjumpc);
    and a9(jumpnc, enable, wjumpnc);
    and a10(sub, enable, wsub);
    and a11(bitand, enable, wbitand);
    

endmodule

FlipFlop/FDPE.v
module FDPE (d, clock, clock_enable, preset, q);
    input d, clock, clock_enable, preset;
    output q;

    wire w1, w2, w3, w4, w5, w6;

    and a1(w1, clock, clock_enable);
    nand na1(w2, d, w1);
    not n1(w3, d);
    nand na2(w4, w1, w3);
    nand na3(w5, w2, w6);
    nand na4(w6, w5, w4);
    or o1(q, preset, w5);
    
endmodule

FlipFlop/FDCE.v
module FDCE (d, clock, clock_enable, clear, q);
    input d, clock, clock_enable, clear;
    output reg q;

    always @(posedge clock) begin
        if(clock_enable == 1 & clear == 0) begin
            q = d;
        end
    end

    always @(clear) begin
        if(clear == 1) begin
            q = 0;
        end
    end
    
endmodule

Decoder/SequenceGenerator.v
/*`include "../FlipFlop/FDCE.v"
`include "../FlipFlop/FDPE.v"*/
module SequenceGenerator (clock, clock_enable, clear, fetch, decode, execute, increment);
    input clock, clock_enable, clear;
    output reg fetch, decode, execute, increment;

    /*FDPE fdpe1(increment, clock, clock_enable, clear, fetch);
    FDCE fdce1(fetch, clock, clock_enable, clear, decode);
    FDCE fdce2(decode, clock, clock_enable, clear, execute);
    FDCE fdce3(execute, clock, clock_enable, clear, increment);*/

    always @(clear) begin
        if(clear == 1) begin
            fetch = 1;
            decode = 0;
            execute = 0;
            increment = 0;
        end
    end

    always @(posedge clock) begin
        if(clock_enable == 1 & clear == 0) begin
            if(fetch == 1) begin
                fetch = 0;
                decode = 1;
            end
            else if(decode == 1) begin
                decode = 0;
                execute = 1;
            end
            else if(execute == 1) begin
                execute = 0;
                increment = 1;
            end
            else if(increment == 1) begin
                increment = 0;
                fetch = 1;
            end
        end
    end

endmodule

Decoder/CompleteInstructionDecoder_t.v
/*`include "SequenceGenerator.v"
`include "CompleteInstructionDecoder.v"*/
module CompleteInstructionDecoder_t ();
    reg[7:0] input_a;
    reg clock,
        input_clock_enable,
        input_clear,
        fetch, 
        decode, 
        execute, 
        increment;
    reg output_ip, 
        output_op, 
        output_load, 
        output_add, 
        output_jump, 
        output_jumpz, 
        output_jumpnz, 
        output_jumpc, 
        output_jumpnc, 
        output_sub, 
        output_bitand;

    SequenceGenerator SG(clock, 
                         input_clock_enable, 
                         input_clear, 
                         fetch, 
                         decode, 
                         execute,
                         increment);
    CompleteInstructionDecoder CID(input_a, decode, execute, output_ip, 
        output_op, 
        output_load, 
        output_add, 
        output_jump, 
        output_jumpz, 
        output_jumpnz, 
        output_jumpc, 
        output_jumpnc, 
        output_sub, 
        output_bitand);

    initial begin
        $dumpfile("CompleteInstructionDecoder.vcd");
        $dumpvars;

        clock = 0;
        input_clear = 1;
        input_clock_enable = 1;
        #100;
        input_clear = 0;

        input_a = 8'b00000000;
        #100;
        input_a = 8'b01000000;
        #100;
        input_a = 8'b00010000;
        #100;
        input_a = 8'b01100000;
        #100;
        input_a = 8'b10100000;
        #100;
        input_a = 8'b11100000;
        #100;
        input_a = 8'b10000000;
        #100;
        input_a = 8'b10010000;
        #100;
        input_a = 8'b10011000;
        #100;
        input_a = 8'b10010100;
        #100;
        input_a = 8'b10011100;
        #100;
        $finish;
    end

    always #20 begin
        clock = ~clock;
    end
    
endmodule

Decoder/CompleteInstructionDecoder.vcd
$date
	Thu Jul 15 22:40:50 2021
$end
$version
	Icarus Verilog
$end
$timescale
	1s
$end
$scope module CompleteInstructionDecoder_t $end
$var wire 1 ! output_sub $end
$var wire 1 " output_op $end
$var wire 1 # output_load $end
$var wire 1 $ output_jumpz $end
$var wire 1 % output_jumpnz $end
$var wire 1 & output_jumpnc $end
$var wire 1 ' output_jumpc $end
$var wire 1 ( output_jump $end
$var wire 1 ) output_ip $end
$var wire 1 * output_bitand $end
$var wire 1 + output_add $end
$var wire 1 , increment $end
$var wire 1 - fetch $end
$var wire 1 . execute $end
$var wire 1 / decode $end
$var reg 1 0 clock $end
$var reg 8 1 input_a [7:0] $end
$var reg 1 2 input_clear $end
$var reg 1 3 input_clock_enable $end
$scope module CID $end
$var wire 8 4 a [7:0] $end
$var wire 1 + add $end
$var wire 1 * bitand $end
$var wire 1 5 enable $end
$var wire 1 ) ip $end
$var wire 1 ( jump $end
$var wire 1 ' jumpc $end
$var wire 1 & jumpnc $end
$var wire 1 % jumpnz $end
$var wire 1 $ jumpz $end
$var wire 1 # load $end
$var wire 1 " op $end
$var wire 1 ! sub $end
$var wire 1 6 wsub $end
$var wire 1 7 wop $end
$var wire 1 8 wload $end
$var wire 1 9 wjumpz $end
$var wire 1 : wjumpnz $end
$var wire 1 ; wjumpnc $end
$var wire 1 < wjumpc $end
$var wire 1 = wjump $end
$var wire 1 > wip $end
$var wire 1 ? wbitand $end
$var wire 1 @ wadd $end
$var wire 1 . execute $end
$var wire 1 / decode $end
$scope module ID $end
$var wire 8 A a [7:0] $end
$var reg 1 @ add $end
$var reg 1 ? bitand $end
$var reg 1 > ip $end
$var reg 1 = jump $end
$var reg 1 < jumpc $end
$var reg 1 ; jumpnc $end
$var reg 1 : jumpnz $end
$var reg 1 9 jumpz $end
$var reg 1 8 load $end
$var reg 1 7 op $end
$var reg 1 6 sub $end
$scope task jump_condition $end
$var reg 1 B a2 $end
$var reg 1 C a3 $end
$upscope $end
$upscope $end
$upscope $end
$scope module SG $end
$var wire 1 2 clear $end
$var wire 1 0 clock $end
$var wire 1 3 clock_enable $end
$var reg 1 / decode $end
$var reg 1 . execute $end
$var reg 1 - fetch $end
$var reg 1 , increment $end
$upscope $end
$upscope $end
$enddefinitions $end
#0
$dumpvars
xC
xB
bx A
x@
x?
x>
x=
x<
x;
x:
x9
x8
x7
x6
05
bx 4
13
12
bx 1
00
0/
0.
1-
0,
0+
0*
0)
0(
0'
0&
0%
0$
0#
0"
0!
$end
#20
10
#40
00
#60
10
#80
00
#100
1#
15
1/
0-
0?
06
0;
0<
0:
09
0=
0@
18
07
0>
10
b0 1
b0 4
b0 A
02
#120
00
#140
1.
0/
10
#160
00
#180
0#
05
1,
0.
10
#200
1@
08
00
b1000000 1
b1000000 4
b1000000 A
#220
1-
0,
10
#240
00
#260
1+
15
1/
0-
10
#280
00
#300
1*
0+
1.
0/
1?
0@
10
b10000 1
b10000 4
b10000 A
#320
00
#340
0*
05
1,
0.
10
#360
00
#380
1-
0,
10
#400
0?
16
00
b1100000 1
b1100000 4
b1100000 A
#420
1!
15
1/
0-
10
#440
00
#460
1.
0/
10
#480
00
#500
05
0!
0)
1,
0.
06
1>
10
b10100000 1
b10100000 4
b10100000 A
#520
00
#540
1-
0,
10
#560
00
#580
1)
15
1/
0-
10
#600
1"
0)
17
0>
00
b11100000 1
b11100000 4
b11100000 A
#620
1.
0/
10
#640
00
#660
0"
05
1,
0.
10
#680
00
#700
1-
0,
1=
07
10
b10000000 1
b10000000 4
b10000000 A
#720
00
#740
1(
15
1/
0-
10
#760
00
#780
1.
0/
10
#800
1$
0(
19
0B
0C
0=
00
b10010000 1
b10010000 4
b10010000 A
#820
0$
05
1,
0.
10
#840
00
#860
1-
0,
10
#880
00
#900
1'
15
1/
0-
1<
09
1C
10
b10011000 1
b10011000 4
b10011000 A
#920
00
#940
1.
0/
10
#960
00
#980
0'
05
1,
0.
10
#1000
0<
1:
1B
0C
00
b10010100 1
b10010100 4
b10010100 A
#1020
1-
0,
10
#1040
00
#1060
1%
15
1/
0-
10
#1080
00
#1100
1&
0%
1.
0/
1;
0:
1C
10
b10011100 1
b10011100 4
b10011100 A
#1120
00
#1140
0&
05
1,
0.
10
#1160
00
#1180
1-
0,
10
