Decoder/InstructionDecoder.v
module InstructionDecoder (a, ip, op, load, add, jump, jumpz, jumpnz, jumpc, jumpnc, sub, bitand);
    input [7:0] a;
    output reg ip, op, load, add, jump, jumpz, jumpnz, jumpc, jumpnc, sub, bitand;



    always @(a) begin
        ip = a[7] && !a[6] && a[5] && !a[4];
        op = a[7] && a[6] && a[5] && !a[4];
        load = !a[7] && !a[6] && !a[5] && !a[4];
        add = !a[7] && a[6] && !a[5] && !a[4];
        jump = a[7] && !a[6] && !a[5] && !a[4];
        if(a[7] && !a[6] && !a[5] && a[4]) begin
            jump_condition(a[3], a[2]);
        end
        else begin
            jumpz = 0;
            jumpnz = 0;
            jumpc = 0;
            jumpnc = 0;
        end
        sub = !a[7] && a[6] && a[5] && !a[4];
        bitand = !a[7] && !a[6] && !a[5] && a[4];
    end

    task jump_condition(a3, a2);
        jumpz = !a3 && !a2;
        jumpnz = !a3 && a2;
        jumpc = a3 && !a2;
        jumpnc = a3 && a2;
    endtask

endmodule

Decoder/InstructionDecoder_t.v
//`include "InstructionDecoder.v"
module InstructionDecoder_t ();
    reg[7:0] input_a;
    reg output_ip, 
        output_op, 
        output_load, 
        output_add, 
        output_jump, 
        output_jumpz, 
        output_jumpnz, 
        output_jumpc, 
        output_jumpnc, 
        output_sub, 
        output_bitand;

    InstructionDecoder id(input_a, output_ip, 
        output_op, 
        output_load, 
        output_add, 
        output_jump, 
        output_jumpz, 
        output_jumpnz, 
        output_jumpc, 
        output_jumpnc, 
        output_sub, 
        output_bitand);

    initial begin
        $dumpfile("InstructionDecoder.vcd");
        $dumpvars;
        input_a = 8'b00000000;
        #50;
        input_a = 8'b01000000;
        #50;
        input_a = 8'b00010000;
        #50;
        input_a = 8'b01100000;
        #50;
        input_a = 8'b10100000;
        #50;
        input_a = 8'b11100000;
        #50;
        input_a = 8'b10000000;
        #50;
        input_a = 8'b10010000;
        #50;
        input_a = 8'b10011000;
        #50;
        input_a = 8'b10010100;
        #50;
        input_a = 8'b10011100;
        #50;
        $finish;
    end

endmodule

Decoder/InstructionDecoder.vcd
$date
	Thu Jul 15 22:29:40 2021
$end
$version
	Icarus Verilog
$end
$timescale
	1s
$end
$scope module InstructionDecoder_t $end
$var wire 1 ! output_sub $end
$var wire 1 " output_op $end
$var wire 1 # output_load $end
$var wire 1 $ output_jumpz $end
$var wire 1 % output_jumpnz $end
$var wire 1 & output_jumpnc $end
$var wire 1 ' output_jumpc $end
$var wire 1 ( output_jump $end
$var wire 1 ) output_ip $end
$var wire 1 * output_bitand $end
$var wire 1 + output_add $end
$var reg 8 , input_a [7:0] $end
$scope module id $end
$var wire 8 - a [7:0] $end
$var reg 1 + add $end
$var reg 1 * bitand $end
$var reg 1 ) ip $end
$var reg 1 ( jump $end
$var reg 1 ' jumpc $end
$var reg 1 & jumpnc $end
$var reg 1 % jumpnz $end
$var reg 1 $ jumpz $end
$var reg 1 # load $end
$var reg 1 " op $end
$var reg 1 ! sub $end
$scope task jump_condition $end
$var reg 1 . a2 $end
$var reg 1 / a3 $end
$upscope $end
$upscope $end
$upscope $end
$enddefinitions $end
#0
$dumpvars
x/
x.
b0 -
b0 ,
0+
0*
0)
0(
0'
0&
0%
0$
1#
0"
0!
$end
#50
1+
0#
b1000000 ,
b1000000 -
#100
1*
0+
b10000 ,
b10000 -
#150
0*
1!
b1100000 ,
b1100000 -
#200
0!
1)
b10100000 ,
b10100000 -
#250
1"
0)
b11100000 ,
b11100000 -
#300
1(
0"
b10000000 ,
b10000000 -
#350
1$
0.
0/
0(
b10010000 ,
b10010000 -
#400
1'
0$
1/
b10011000 ,
b10011000 -
#450
0'
1%
1.
0/
b10010100 ,
b10010100 -
#500
1&
0%
1/
b10011100 ,
b10011100 -
