Decoder/SequenceGenerator.v
/*`include "../FlipFlop/FDCE.v"
`include "../FlipFlop/FDPE.v"*/
module SequenceGenerator (clock, clock_enable, clear, fetch, decode, execute, increment);
    input clock, clock_enable, clear;
    output reg fetch, decode, execute, increment;

    /*FDPE fdpe1(increment, clock, clock_enable, clear, fetch);
    FDCE fdce1(fetch, clock, clock_enable, clear, decode);
    FDCE fdce2(decode, clock, clock_enable, clear, execute);
    FDCE fdce3(execute, clock, clock_enable, clear, increment);*/

    always @(clear) begin
        if(clear == 1) begin
            fetch = 1;
            decode = 0;
            execute = 0;
            increment = 0;
        end
    end

    always @(posedge clock) begin
        if(clock_enable == 1 & clear == 0) begin
            if(fetch == 1) begin
                fetch = 0;
                decode = 1;
            end
            else if(decode == 1) begin
                decode = 0;
                execute = 1;
            end
            else if(execute == 1) begin
                execute = 0;
                increment = 1;
            end
            else if(increment == 1) begin
                increment = 0;
                fetch = 1;
            end
        end
    end

endmodule

Decoder/SequenceGenerator_t.v
//`include "SequenceGenerator.v"
module SequenceGenerator_t ();
    reg clock, 
        input_clock_enable, 
        input_clear, 
        output_fetch, 
        output_decode, 
        output_execute, 
        output_increment;

    SequenceGenerator sg(clock, 
                         input_clock_enable, 
                         input_clear, 
                         output_fetch, 
                         output_decode, 
                         output_execute,
                         output_increment);
    
    task test(CE, CLR);
        input_clock_enable = CE;
        input_clear = CLR;
        #100;
    endtask

    initial begin
        clock = 0;
        $dumpfile("SequenceGenerator.vcd");
        $dumpvars;

        test(1, 1);
        test(1, 0);
        test(1, 0);
        #100;
        $finish;
    end

    always #20 begin
        clock = ~clock;
    end
    
endmodule

FlipFlop/FDPE.v
module FDPE (d, clock, clock_enable, preset, q);
    input d, clock, clock_enable, preset;
    output q;

    wire w1, w2, w3, w4, w5, w6;

    and a1(w1, clock, clock_enable);
    nand na1(w2, d, w1);
    not n1(w3, d);
    nand na2(w4, w1, w3);
    nand na3(w5, w2, w6);
    nand na4(w6, w5, w4);
    or o1(q, preset, w5);
    
endmodule

FlipFlop/FDCE.v
module FDCE (d, clock, clock_enable, clear, q);
    input d, clock, clock_enable, clear;
    output reg q;

    always @(posedge clock) begin
        if(clock_enable == 1 & clear == 0) begin
            q = d;
        end
    end

    always @(clear) begin
        if(clear == 1) begin
            q = 0;
        end
    end
    
endmodule

Decoder/SequenceGenerator.vcd
$date
	Thu Jul 15 22:29:40 2021
$end
$version
	Icarus Verilog
$end
$timescale
	1s
$end
$scope module FDCE $end
$var wire 1 ! clear $end
$var wire 1 " clock $end
$var wire 1 # clock_enable $end
$var wire 1 $ d $end
$var reg 1 % q $end
$upscope $end
$scope module FDPE $end
$var wire 1 & clock $end
$var wire 1 ' clock_enable $end
$var wire 1 ( d $end
$var wire 1 ) preset $end
$var reg 1 * q $end
$upscope $end
$scope module SequenceGenerator_t $end
$var wire 1 + output_increment $end
$var wire 1 , output_fetch $end
$var wire 1 - output_execute $end
$var wire 1 . output_decode $end
$var reg 1 / clock $end
$var reg 1 0 input_clear $end
$var reg 1 1 input_clock_enable $end
$scope module sg $end
$var wire 1 0 clear $end
$var wire 1 / clock $end
$var wire 1 1 clock_enable $end
$var reg 1 . decode $end
$var reg 1 - execute $end
$var reg 1 , fetch $end
$var reg 1 + increment $end
$upscope $end
$scope task test $end
$var reg 1 2 CE $end
$var reg 1 3 CLR $end
$upscope $end
$upscope $end
$enddefinitions $end
#0
$dumpvars
13
12
11
10
0/
0.
0-
1,
0+
x*
z)
z(
z'
z&
x%
z$
z#
z"
z!
$end
#20
1/
#40
0/
#60
1/
#80
0/
#100
1.
0,
1/
00
03
#120
0/
#140
1-
0.
1/
#160
0/
#180
1+
0-
1/
#200
0/
#220
1,
0+
1/
#240
0/
#260
1.
0,
1/
#280
0/
#300
1-
0.
1/
#320
0/
#340
1+
0-
1/
#360
0/
#380
1,
0+
1/
