MUX/MUX_2to1_1B.v
module MUX_2to1_1B (
	input a,
	input b,
	input select,
	output result);
	wire w1, w2, w3;

	not not1(w1, select);
	and and1(w2, a, w1);
	and and2(w3, select, b);
	or or1(result, w2, w3);

endmodule

MUX/MUX_2to1_8B.v
//`include "MUX_2to1_1B.v"
module MUX_2to1_8B (
	input[7:0] a,
	input[7:0] b,
	input select,
	output[7:0] result);
	
	MUX_2to1_1B m1(a[0], b[0], select, result[0]);
	MUX_2to1_1B m2(a[1], b[1], select, result[1]);
	MUX_2to1_1B m3(a[2], b[2], select, result[2]);
	MUX_2to1_1B m4(a[3], b[3], select, result[3]);
	MUX_2to1_1B m5(a[4], b[4], select, result[4]);
	MUX_2to1_1B m6(a[5], b[5], select, result[5]);
	MUX_2to1_1B m7(a[6], b[6], select, result[6]);
	MUX_2to1_1B m8(a[7], b[7], select, result[7]);
	

endmodule

MUX/MUX_4to1_8B.v
//`include "MUX_2to1_8B.v"
module MUX_4to1_8B (
	input[7:0] a,
	input[7:0] b,
	input[7:0] c,
	input[7:0] d,
	input select0,
	input select1,
	output[7:0] result
);
	wire[7:0] w1, w2;
	
	MUX_2to1_8B m1(a, b, select0, w1);
	MUX_2to1_8B m2(c, d, select0, w2);
	MUX_2to1_8B m3(w1, w2, select1, result);

endmodule

8BitGate/AndGate_8B.v
module AndGate_8B (a, b, z);
    input[7:0] a, b;
    output[7:0] z;

    and a1(z[0], a[0], b[0]);
    and a2(z[1], a[1], b[1]);
    and a3(z[2], a[2], b[2]);
    and a4(z[3], a[3], b[3]);
    and a5(z[4], a[4], b[4]);
    and a6(z[5], a[5], b[5]);
    and a7(z[6], a[6], b[6]);
    and a8(z[7], a[7], b[7]);
    
    
endmodule

ALU/HalfAdder_1B.v
module HalfAdder_1B (a, b, carry_out, sum);
    input a, b;
    output carry_out, sum;

    and and1(carry_out, a, b);
    xor xor1(sum, a, b);
    
endmodule

ALU/FullAdder_1B.v
//`include "HalfAdder_1B.v"
module FullAdder_1B (a, b, carry_in, carry_out, sum);
    input a, b, carry_in;
    output carry_out, sum;

    wire w1, w2, w3;

    HalfAdder_1B h1(a, b, w1, w2);
    HalfAdder_1B h2(w2, carry_in, w3, sum);
    or o1(carry_out, w1, w3);
    
endmodule

ALU/FullAdder_8B.v
//`include "FullAdder_1B.v" 
module FullAdder_8B (a, b, carry_in, carry_out, sum);
    input[7:0] a, b;
    input carry_in;
    output carry_out;
    output[7:0] sum;
    wire[6:0] carry_temp;

    FullAdder_1B f1(a[0], b[0], carry_in, carry_temp[0], sum[0]);
    FullAdder_1B f2(a[1], b[1], carry_temp[0], carry_temp[1], sum[1]);
    FullAdder_1B f3(a[2], b[2], carry_temp[1], carry_temp[2], sum[2]);
    FullAdder_1B f4(a[3], b[3], carry_temp[2], carry_temp[3], sum[3]);
    FullAdder_1B f5(a[4], b[4], carry_temp[3], carry_temp[4], sum[4]);
    FullAdder_1B f6(a[5], b[5], carry_temp[4], carry_temp[5], sum[5]);
    FullAdder_1B f7(a[6], b[6], carry_temp[5], carry_temp[6], sum[6]);
    FullAdder_1B f8(a[7], b[7], carry_temp[6], carry_out, sum[7]);
    
    
endmodule

8BitGate/Inverter_8B.v
module Inverter_8B (a, enable, z);
    input[7:0] a;
    input enable;
    output[7:0] z;

    xor x1(z[0], a[0], enable);
    xor x2(z[1], a[1], enable);
    xor x3(z[2], a[2], enable);
    xor x4(z[3], a[3], enable);
    xor x5(z[4], a[4], enable);
    xor x6(z[5], a[5], enable);
    xor x7(z[6], a[6], enable);
    xor x8(z[7], a[7], enable);
    
    
endmodule

8BitGate/Replicater_8B.v
module Replicater_8B (a, z);
    input a;
    output[7:0] z;

    assign z[0] = a;
    assign z[1] = a;
    assign z[2] = a;
    assign z[3] = a;
    assign z[4] = a;
    assign z[5] = a;
    assign z[6] = a;
    assign z[7] = a;
    

endmodule

ALU/ALU.v
`include "../8BitGate/Replicater_8B.v"
`include "../8BitGate/Inverter_8B.v"
`include "../8BitGate/AndGate_8B.v"
`include "FullAdder_8B.v"
`include "../MUX/MUX_4to1_8B.v"
module ALU (a, b, s0, s1, s2, s3, s4, z, carry_out);
    input[7:0] a, b;
    input s0, s1, s2, s3, s4;
    output[7:0] z;
    output carry_out;

    wire w1;
    wire[7:0] w2, w3, w4, w5, w6;

    xor x1(w1, s4, 1);
    Replicater_8B b1(w1, w2);
    Inverter_8B i1(b, s3, w3);
    AndGate_8B a1(w2, w3, w4);
    FullAdder_8B f1(a, w4, s2, carry_out, w5);
    AndGate_8B a2(a, b, w6);
    MUX_4to1_8B m1(w5, w6, a, b, s0, s1, z);

    
endmodule

ALU/ALU_t.v
//`include "ALU.v"
module ALU_t ();
    reg[7:0] input_a, input_b, output_data;
    reg input_s0, input_s1, input_s2, input_s3, input_s4, output_carry;

    ALU a(input_a, input_b, input_s0, input_s1, input_s2, input_s3, input_s4, output_data, output_carry);

    task test(S0, S1, S2, S3, S4);
        input_s0 = S0;
        input_s1 = S1;
        input_s2 = S2;
        input_s3 = S3;
        input_s4 = S4;
        #100;
    endtask

    initial begin
        $dumpfile("ALU.vcd");
        $dumpvars;

        input_a = 8'b11111000;
        input_b = 8'b00011111;

        test(0, 0, 0, 0, 0);
        test(1, 0, 0, 0, 0);
        test(0, 1, 0, 0, 0);
        test(1, 1, 0, 0, 0);
        test(0, 0, 1, 1, 0);
        test(0, 0, 1, 0, 1);
        test(0, 0, 0, 0, 1);
        test(0, 0, 1, 0, 0);
        test(0, 0, 0, 1, 0);
        $finish;
        

    end
    
endmodule

ALU/ALU.vcd
$date
	Tue Jul 13 20:28:29 2021
$end
$version
	Icarus Verilog
$end
$timescale
	1s
$end
$scope module ALU_t $end
$var wire 8 ! output_data [7:0] $end
$var wire 1 " output_carry $end
$var reg 8 # input_a [7:0] $end
$var reg 8 $ input_b [7:0] $end
$var reg 1 % input_s0 $end
$var reg 1 & input_s1 $end
$var reg 1 ' input_s2 $end
$var reg 1 ( input_s3 $end
$var reg 1 ) input_s4 $end
$scope module a $end
$var wire 8 * a [7:0] $end
$var wire 8 + b [7:0] $end
$var wire 1 % s0 $end
$var wire 1 & s1 $end
$var wire 1 ' s2 $end
$var wire 1 ( s3 $end
$var wire 1 ) s4 $end
$var wire 1 , w1 $end
$var wire 8 - z [7:0] $end
$var wire 8 . w6 [7:0] $end
$var wire 8 / w5 [7:0] $end
$var wire 8 0 w4 [7:0] $end
$var wire 8 1 w3 [7:0] $end
$var wire 8 2 w2 [7:0] $end
$var wire 1 " carry_out $end
$scope module a1 $end
$var wire 8 3 z [7:0] $end
$var wire 8 4 b [7:0] $end
$var wire 8 5 a [7:0] $end
$upscope $end
$scope module a2 $end
$var wire 8 6 a [7:0] $end
$var wire 8 7 b [7:0] $end
$var wire 8 8 z [7:0] $end
$upscope $end
$scope module b1 $end
$var wire 1 , a $end
$var wire 8 9 z [7:0] $end
$upscope $end
$scope module f1 $end
$var wire 8 : a [7:0] $end
$var wire 8 ; b [7:0] $end
$var wire 1 ' carry_in $end
$var wire 8 < sum [7:0] $end
$var wire 7 = carry_temp [6:0] $end
$var wire 1 " carry_out $end
$scope module f1 $end
$var wire 1 > a $end
$var wire 1 ? b $end
$var wire 1 ' carry_in $end
$var wire 1 @ carry_out $end
$var wire 1 A w3 $end
$var wire 1 B w2 $end
$var wire 1 C w1 $end
$var wire 1 D sum $end
$scope module h1 $end
$var wire 1 > a $end
$var wire 1 ? b $end
$var wire 1 C carry_out $end
$var wire 1 B sum $end
$upscope $end
$scope module h2 $end
$var wire 1 B a $end
$var wire 1 ' b $end
$var wire 1 A carry_out $end
$var wire 1 D sum $end
$upscope $end
$upscope $end
$scope module f2 $end
$var wire 1 E a $end
$var wire 1 F b $end
$var wire 1 G carry_in $end
$var wire 1 H carry_out $end
$var wire 1 I w3 $end
$var wire 1 J w2 $end
$var wire 1 K w1 $end
$var wire 1 L sum $end
$scope module h1 $end
$var wire 1 E a $end
$var wire 1 F b $end
$var wire 1 K carry_out $end
$var wire 1 J sum $end
$upscope $end
$scope module h2 $end
$var wire 1 J a $end
$var wire 1 G b $end
$var wire 1 I carry_out $end
$var wire 1 L sum $end
$upscope $end
$upscope $end
$scope module f3 $end
$var wire 1 M a $end
$var wire 1 N b $end
$var wire 1 O carry_in $end
$var wire 1 P carry_out $end
$var wire 1 Q w3 $end
$var wire 1 R w2 $end
$var wire 1 S w1 $end
$var wire 1 T sum $end
$scope module h1 $end
$var wire 1 M a $end
$var wire 1 N b $end
$var wire 1 S carry_out $end
$var wire 1 R sum $end
$upscope $end
$scope module h2 $end
$var wire 1 R a $end
$var wire 1 O b $end
$var wire 1 Q carry_out $end
$var wire 1 T sum $end
$upscope $end
$upscope $end
$scope module f4 $end
$var wire 1 U a $end
$var wire 1 V b $end
$var wire 1 W carry_in $end
$var wire 1 X carry_out $end
$var wire 1 Y w3 $end
$var wire 1 Z w2 $end
$var wire 1 [ w1 $end
$var wire 1 \ sum $end
$scope module h1 $end
$var wire 1 U a $end
$var wire 1 V b $end
$var wire 1 [ carry_out $end
$var wire 1 Z sum $end
$upscope $end
$scope module h2 $end
$var wire 1 Z a $end
$var wire 1 W b $end
$var wire 1 Y carry_out $end
$var wire 1 \ sum $end
$upscope $end
$upscope $end
$scope module f5 $end
$var wire 1 ] a $end
$var wire 1 ^ b $end
$var wire 1 _ carry_in $end
$var wire 1 ` carry_out $end
$var wire 1 a w3 $end
$var wire 1 b w2 $end
$var wire 1 c w1 $end
$var wire 1 d sum $end
$scope module h1 $end
$var wire 1 ] a $end
$var wire 1 ^ b $end
$var wire 1 c carry_out $end
$var wire 1 b sum $end
$upscope $end
$scope module h2 $end
$var wire 1 b a $end
$var wire 1 _ b $end
$var wire 1 a carry_out $end
$var wire 1 d sum $end
$upscope $end
$upscope $end
$scope module f6 $end
$var wire 1 e a $end
$var wire 1 f b $end
$var wire 1 g carry_in $end
$var wire 1 h carry_out $end
$var wire 1 i w3 $end
$var wire 1 j w2 $end
$var wire 1 k w1 $end
$var wire 1 l sum $end
$scope module h1 $end
$var wire 1 e a $end
$var wire 1 f b $end
$var wire 1 k carry_out $end
$var wire 1 j sum $end
$upscope $end
$scope module h2 $end
$var wire 1 j a $end
$var wire 1 g b $end
$var wire 1 i carry_out $end
$var wire 1 l sum $end
$upscope $end
$upscope $end
$scope module f7 $end
$var wire 1 m a $end
$var wire 1 n b $end
$var wire 1 o carry_in $end
$var wire 1 p carry_out $end
$var wire 1 q w3 $end
$var wire 1 r w2 $end
$var wire 1 s w1 $end
$var wire 1 t sum $end
$scope module h1 $end
$var wire 1 m a $end
$var wire 1 n b $end
$var wire 1 s carry_out $end
$var wire 1 r sum $end
$upscope $end
$scope module h2 $end
$var wire 1 r a $end
$var wire 1 o b $end
$var wire 1 q carry_out $end
$var wire 1 t sum $end
$upscope $end
$upscope $end
$scope module f8 $end
$var wire 1 u a $end
$var wire 1 v b $end
$var wire 1 w carry_in $end
$var wire 1 " carry_out $end
$var wire 1 x w3 $end
$var wire 1 y w2 $end
$var wire 1 z w1 $end
$var wire 1 { sum $end
$scope module h1 $end
$var wire 1 u a $end
$var wire 1 v b $end
$var wire 1 z carry_out $end
$var wire 1 y sum $end
$upscope $end
$scope module h2 $end
$var wire 1 y a $end
$var wire 1 w b $end
$var wire 1 x carry_out $end
$var wire 1 { sum $end
$upscope $end
$upscope $end
$upscope $end
$scope module i1 $end
$var wire 8 | a [7:0] $end
$var wire 1 ( enable $end
$var wire 8 } z [7:0] $end
$upscope $end
$scope module m1 $end
$var wire 8 ~ a [7:0] $end
$var wire 8 !" b [7:0] $end
$var wire 8 "" c [7:0] $end
$var wire 8 #" d [7:0] $end
$var wire 1 % select0 $end
$var wire 1 & select1 $end
$var wire 8 $" w2 [7:0] $end
$var wire 8 %" w1 [7:0] $end
$var wire 8 &" result [7:0] $end
$scope module m1 $end
$var wire 8 '" a [7:0] $end
$var wire 8 (" b [7:0] $end
$var wire 1 % select $end
$var wire 8 )" result [7:0] $end
$scope module m1 $end
$var wire 1 *" a $end
$var wire 1 +" b $end
$var wire 1 ," result $end
$var wire 1 % select $end
$var wire 1 -" w1 $end
$var wire 1 ." w2 $end
$var wire 1 /" w3 $end
$upscope $end
$scope module m2 $end
$var wire 1 0" a $end
$var wire 1 1" b $end
$var wire 1 2" result $end
$var wire 1 % select $end
$var wire 1 3" w1 $end
$var wire 1 4" w2 $end
$var wire 1 5" w3 $end
$upscope $end
$scope module m3 $end
$var wire 1 6" a $end
$var wire 1 7" b $end
$var wire 1 8" result $end
$var wire 1 % select $end
$var wire 1 9" w1 $end
$var wire 1 :" w2 $end
$var wire 1 ;" w3 $end
$upscope $end
$scope module m4 $end
$var wire 1 <" a $end
$var wire 1 =" b $end
$var wire 1 >" result $end
$var wire 1 % select $end
$var wire 1 ?" w1 $end
$var wire 1 @" w2 $end
$var wire 1 A" w3 $end
$upscope $end
$scope module m5 $end
$var wire 1 B" a $end
$var wire 1 C" b $end
$var wire 1 D" result $end
$var wire 1 % select $end
$var wire 1 E" w1 $end
$var wire 1 F" w2 $end
$var wire 1 G" w3 $end
$upscope $end
$scope module m6 $end
$var wire 1 H" a $end
$var wire 1 I" b $end
$var wire 1 J" result $end
$var wire 1 % select $end
$var wire 1 K" w1 $end
$var wire 1 L" w2 $end
$var wire 1 M" w3 $end
$upscope $end
$scope module m7 $end
$var wire 1 N" a $end
$var wire 1 O" b $end
$var wire 1 P" result $end
$var wire 1 % select $end
$var wire 1 Q" w1 $end
$var wire 1 R" w2 $end
$var wire 1 S" w3 $end
$upscope $end
$scope module m8 $end
$var wire 1 T" a $end
$var wire 1 U" b $end
$var wire 1 V" result $end
$var wire 1 % select $end
$var wire 1 W" w1 $end
$var wire 1 X" w2 $end
$var wire 1 Y" w3 $end
$upscope $end
$upscope $end
$scope module m2 $end
$var wire 8 Z" a [7:0] $end
$var wire 8 [" b [7:0] $end
$var wire 1 % select $end
$var wire 8 \" result [7:0] $end
$scope module m1 $end
$var wire 1 ]" a $end
$var wire 1 ^" b $end
$var wire 1 _" result $end
$var wire 1 % select $end
$var wire 1 `" w1 $end
$var wire 1 a" w2 $end
$var wire 1 b" w3 $end
$upscope $end
$scope module m2 $end
$var wire 1 c" a $end
$var wire 1 d" b $end
$var wire 1 e" result $end
$var wire 1 % select $end
$var wire 1 f" w1 $end
$var wire 1 g" w2 $end
$var wire 1 h" w3 $end
$upscope $end
$scope module m3 $end
$var wire 1 i" a $end
$var wire 1 j" b $end
$var wire 1 k" result $end
$var wire 1 % select $end
$var wire 1 l" w1 $end
$var wire 1 m" w2 $end
$var wire 1 n" w3 $end
$upscope $end
$scope module m4 $end
$var wire 1 o" a $end
$var wire 1 p" b $end
$var wire 1 q" result $end
$var wire 1 % select $end
$var wire 1 r" w1 $end
$var wire 1 s" w2 $end
$var wire 1 t" w3 $end
$upscope $end
$scope module m5 $end
$var wire 1 u" a $end
$var wire 1 v" b $end
$var wire 1 w" result $end
$var wire 1 % select $end
$var wire 1 x" w1 $end
$var wire 1 y" w2 $end
$var wire 1 z" w3 $end
$upscope $end
$scope module m6 $end
$var wire 1 {" a $end
$var wire 1 |" b $end
$var wire 1 }" result $end
$var wire 1 % select $end
$var wire 1 ~" w1 $end
$var wire 1 !# w2 $end
$var wire 1 "# w3 $end
$upscope $end
$scope module m7 $end
$var wire 1 ## a $end
$var wire 1 $# b $end
$var wire 1 %# result $end
$var wire 1 % select $end
$var wire 1 &# w1 $end
$var wire 1 '# w2 $end
$var wire 1 (# w3 $end
$upscope $end
$scope module m8 $end
$var wire 1 )# a $end
$var wire 1 *# b $end
$var wire 1 +# result $end
$var wire 1 % select $end
$var wire 1 ,# w1 $end
$var wire 1 -# w2 $end
$var wire 1 .# w3 $end
$upscope $end
$upscope $end
$scope module m3 $end
$var wire 8 /# a [7:0] $end
$var wire 8 0# b [7:0] $end
$var wire 1 & select $end
$var wire 8 1# result [7:0] $end
$scope module m1 $end
$var wire 1 2# a $end
$var wire 1 3# b $end
$var wire 1 4# result $end
$var wire 1 & select $end
$var wire 1 5# w1 $end
$var wire 1 6# w2 $end
$var wire 1 7# w3 $end
$upscope $end
$scope module m2 $end
$var wire 1 8# a $end
$var wire 1 9# b $end
$var wire 1 :# result $end
$var wire 1 & select $end
$var wire 1 ;# w1 $end
$var wire 1 <# w2 $end
$var wire 1 =# w3 $end
$upscope $end
$scope module m3 $end
$var wire 1 ># a $end
$var wire 1 ?# b $end
$var wire 1 @# result $end
$var wire 1 & select $end
$var wire 1 A# w1 $end
$var wire 1 B# w2 $end
$var wire 1 C# w3 $end
$upscope $end
$scope module m4 $end
$var wire 1 D# a $end
$var wire 1 E# b $end
$var wire 1 F# result $end
$var wire 1 & select $end
$var wire 1 G# w1 $end
$var wire 1 H# w2 $end
$var wire 1 I# w3 $end
$upscope $end
$scope module m5 $end
$var wire 1 J# a $end
$var wire 1 K# b $end
$var wire 1 L# result $end
$var wire 1 & select $end
$var wire 1 M# w1 $end
$var wire 1 N# w2 $end
$var wire 1 O# w3 $end
$upscope $end
$scope module m6 $end
$var wire 1 P# a $end
$var wire 1 Q# b $end
$var wire 1 R# result $end
$var wire 1 & select $end
$var wire 1 S# w1 $end
$var wire 1 T# w2 $end
$var wire 1 U# w3 $end
$upscope $end
$scope module m7 $end
$var wire 1 V# a $end
$var wire 1 W# b $end
$var wire 1 X# result $end
$var wire 1 & select $end
$var wire 1 Y# w1 $end
$var wire 1 Z# w2 $end
$var wire 1 [# w3 $end
$upscope $end
$scope module m8 $end
$var wire 1 \# a $end
$var wire 1 ]# b $end
$var wire 1 ^# result $end
$var wire 1 & select $end
$var wire 1 _# w1 $end
$var wire 1 `# w2 $end
$var wire 1 a# w3 $end
$upscope $end
$upscope $end
$upscope $end
$upscope $end
$scope task test $end
$var reg 1 b# S0 $end
$var reg 1 c# S1 $end
$var reg 1 d# S2 $end
$var reg 1 e# S3 $end
$var reg 1 f# S4 $end
$upscope $end
$upscope $end
$enddefinitions $end
#0
$dumpvars
0f#
0e#
0d#
0c#
0b#
0a#
0`#
1_#
0^#
1]#
0\#
0[#
0Z#
1Y#
0X#
1W#
0V#
0U#
0T#
1S#
0R#
1Q#
0P#
0O#
1N#
1M#
1L#
1K#
1J#
0I#
0H#
1G#
0F#
1E#
0D#
0C#
1B#
1A#
1@#
0?#
1>#
0=#
1<#
1;#
1:#
09#
18#
07#
16#
15#
14#
03#
12#
b10111 1#
b11111000 0#
b10111 /#
0.#
1-#
1,#
1+#
0*#
1)#
0(#
1'#
1&#
1%#
0$#
1##
0"#
1!#
1~"
1}"
0|"
1{"
0z"
1y"
1x"
1w"
1v"
1u"
0t"
1s"
1r"
1q"
1p"
1o"
0n"
0m"
1l"
0k"
1j"
0i"
0h"
0g"
1f"
0e"
1d"
0c"
0b"
0a"
1`"
0_"
1^"
0]"
b11111000 \"
b11111 ["
b11111000 Z"
0Y"
0X"
1W"
0V"
0U"
0T"
0S"
0R"
1Q"
0P"
0O"
0N"
0M"
0L"
1K"
0J"
0I"
0H"
0G"
1F"
1E"
1D"
1C"
1B"
0A"
0@"
1?"
0>"
1="
0<"
0;"
1:"
19"
18"
07"
16"
05"
14"
13"
12"
01"
10"
0/"
1."
1-"
1,"
0+"
1*"
b10111 )"
b11000 ("
b10111 '"
b10111 &"
b10111 %"
b11111000 $"
b11111 #"
b11111000 ""
b11000 !"
b10111 ~
b11111 }
b11111 |
0{
0z
1y
1x
1w
0v
1u
0t
0s
1r
1q
1p
1o
0n
1m
0l
0k
1j
1i
1h
1g
0f
1e
1d
1c
0b
0a
1`
1_
1^
1]
0\
1[
0Z
0Y
1X
0W
1V
1U
1T
0S
1R
0Q
0P
0O
1N
0M
1L
0K
1J
0I
0H
0G
1F
0E
1D
0C
1B
0A
0@
1?
0>
b1111000 =
b10111 <
b11111 ;
b11111000 :
b11111111 9
b11000 8
b11111 7
b11111000 6
b11111111 5
b11111 4
b11111 3
b11111111 2
b11111 1
b11111 0
b10111 /
b11000 .
b10111 -
1,
b11111 +
b11111000 *
0)
0(
0'
0&
0%
b11111 $
b11111000 #
1"
b10111 !
$end
#100
04#
0:#
0@#
06#
0<#
0B#
b11000 !
b11000 -
b11000 &"
b11000 1#
1F#
02#
08#
0>#
1H#
0Q#
0W#
0]#
0,"
02"
08"
1D#
13#
19#
1?#
0}"
0%#
0+#
0."
04"
0:"
b11000 %"
b11000 )"
b11000 /#
1>"
0F"
1_"
1e"
b11111 $"
b11111 \"
b11111 0#
1k"
0s"
0y"
0!#
0'#
0-#
0-"
03"
09"
0?"
1A"
0E"
1G"
0K"
0Q"
0W"
0`"
1b"
0f"
1h"
0l"
1n"
0r"
1t"
0x"
1z"
0~"
0&#
0,#
1%
1b#
#200
1R#
1X#
1^#
1F#
1L#
1U#
1[#
1a#
12#
18#
1>#
1Q#
1W#
1]#
1,"
12"
18"
0D#
1J#
03#
09#
0?#
1E#
1K#
1}"
1%#
1+#
04#
0:#
b11111000 !
b11111000 -
b11111000 &"
b11111000 1#
0@#
0H#
0N#
1."
14"
1:"
0>"
1F"
b10111 %"
b10111 )"
b10111 /#
1D"
0_"
0e"
0k"
1s"
1q"
1y"
b11111000 $"
b11111000 \"
b11111000 0#
1w"
1!#
1'#
1-#
05#
07#
0;#
0=#
0A#
0C#
0G#
1I#
0M#
1O#
0S#
0Y#
0_#
1-"
13"
19"
1?"
0A"
1E"
0G"
1K"
1Q"
1W"
1`"
0b"
1f"
0h"
1l"
0n"
1r"
0t"
1x"
0z"
1~"
1&#
1,#
1&
0%
1c#
0b#
#300
0R#
0X#
0^#
14#
1:#
b11111 !
b11111 -
b11111 &"
b11111 1#
1@#
0U#
0[#
0a#
02#
08#
0>#
17#
1=#
1C#
0Q#
0W#
0]#
0,"
02"
08"
1D#
13#
19#
1?#
0}"
0%#
0+#
0."
04"
0:"
b11000 %"
b11000 )"
b11000 /#
1>"
0F"
1_"
1e"
b11111 $"
b11111 \"
b11111 0#
1k"
0s"
0y"
0!#
0'#
0-#
0-"
03"
09"
0?"
1A"
0E"
1G"
0K"
0Q"
0W"
0`"
1b"
0f"
1h"
0l"
1n"
0r"
1t"
0x"
1z"
0~"
0&#
0,#
1%
1b#
#400
0R#
1X#
1^#
0T#
1Z#
1`#
06"
0g
0P#
1V#
1\#
0T
0`
0J"
1P"
1V"
1@"
0L"
1R"
1X"
0_
1<"
1B"
0H"
1N"
1T"
0X
1\
0a
1d
0i
0l
0q
1t
0x
1{
0O
0B
0J
0R
0[
1Z
0c
1b
1k
0j
1s
0r
1z
0y
0H
00"
16#
0<#
0B#
0?
0F
0N
0V
0^
1f
1n
1v
0I
0L
12#
08#
0>#
1Q#
1W#
1]#
b11100000 0
b11100000 3
b11100000 ;
0G
1,"
02"
08"
1D#
1J#
03#
09#
0?#
1E#
1K#
1}"
1%#
1+#
b1100000 =
0@
1*"
14#
0:#
0@#
1H#
1F#
1N#
b11011001 !
b11011001 -
b11011001 &"
b11011001 1#
1L#
1."
04"
0:"
1>"
1F"
b11011001 %"
b11011001 )"
b11011001 /#
1D"
0_"
0e"
0k"
1s"
1q"
1y"
b11111000 $"
b11111000 \"
b11111000 0#
1w"
1!#
1'#
1-#
b11100000 1
b11100000 4
b11100000 }
0A
b11011001 /
b11011001 <
b11011001 ~
b11011001 '"
1D
15#
07#
1;#
0=#
1A#
0C#
1G#
0I#
1M#
0O#
1S#
1Y#
1_#
1-"
13"
19"
1?"
0A"
1E"
0G"
1K"
1Q"
1W"
1`"
0b"
1f"
0h"
1l"
0n"
1r"
0t"
1x"
0z"
1~"
1&#
1,#
1(
1'
0&
0%
1e#
1d#
0c#
0b#
#500
0"
1R#
1X#
b11111001 !
b11111001 -
b11111001 &"
b11111001 1#
1^#
1T#
1Z#
1`#
0w
1P#
1V#
1\#
0p
1J"
1P"
b11111001 %"
b11111001 )"
b11111001 /#
1V"
1L"
1R"
1X"
0o
1H"
1N"
1T"
b0 =
0h
1l
0q
1t
0x
b11111001 /
b11111001 <
b11111001 ~
b11111001 '"
1{
0k
1j
0s
1r
0z
1y
0f
0n
0v
b0 0
b0 3
b0 ;
b0 2
b0 5
b0 9
0,
b11111 1
b11111 4
b11111 }
1)
0(
1f#
0e#
#600
b11111000 !
b11111000 -
b11111000 &"
b11111000 1#
04#
06#
02#
b11111000 %"
b11111000 )"
b11111000 /#
0,"
0."
0*"
b11111000 /
b11111000 <
b11111000 ~
b11111000 '"
0D
0'
0d#
#700
0^#
0`#
0\#
0V"
0X#
0X"
0Z#
1"
0T"
0V#
1W
1x
0{
0P"
0R#
1P
1w
0R"
0T#
1Q
0:#
0@#
1F#
1p
0N"
0P#
1L#
1O
0<#
0B#
1H#
1q
0t
0J"
1N#
1H
08#
0>#
1D#
1o
0L"
1J#
1I
02"
08"
1>"
1h
0H"
1D"
1G
04"
0:"
1@"
1i
0l
1F"
1@
00"
06"
1_
1<"
1g
1B"
b11000 !
b11000 -
b11000 &"
b11000 1#
04#
1A
0L
0T
1X
1\
b1111111 =
1`
1d
06#
1B
1J
1R
1[
0Z
1c
0b
02#
1?
1F
1N
1V
1^
b11000 %"
b11000 )"
b11000 /#
0,"
b11111 0
b11111 3
b11111 ;
0."
0*"
b11111111 2
b11111111 5
b11111111 9
1,
b11000 /
b11000 <
b11000 ~
b11000 '"
0D
0)
1'
0f#
1d#
#800
0g
0`
1F#
1L#
0R#
1X#
1^#
0_
1H#
1N#
0T#
1Z#
1`#
0X
1D#
1J#
0P#
1V#
1\#
0:#
1>"
1D"
0J"
1P"
1V"
0<#
0W
1@"
1F"
0L"
1R"
1X"
08#
0P
1<"
1B"
0H"
1N"
1T"
02"
b11011000 !
b11011000 -
b11011000 &"
b11011000 1#
04#
0Q
0Y
1\
0a
1d
0i
0l
0q
1t
0x
1{
0O
04"
06#
0B
0J
0R
0[
1Z
0c
1b
1k
0j
1s
0r
1z
0y
0H
00"
02#
0?
0F
0N
0V
0^
1f
1n
1v
0I
0L
b11011000 %"
b11011000 )"
b11011000 /#
0,"
b11100000 0
b11100000 3
b11100000 ;
0G
0."
b1100000 =
0@
0*"
b11100000 1
b11100000 4
b11100000 }
0A
b11011000 /
b11011000 <
b11011000 ~
b11011000 '"
0D
1(
0'
1e#
0d#
