ALU/HalfAdder_1B.v
module HalfAdder_1B (a, b, carry_out, sum);
    input a, b;
    output carry_out, sum;

    and and1(carry_out, a, b);
    xor xor1(sum, a, b);
    
endmodule

ALU/FullAdder_1B.v
//`include "HalfAdder_1B.v"
module FullAdder_1B (a, b, carry_in, carry_out, sum);
    input a, b, carry_in;
    output carry_out, sum;

    wire w1, w2, w3;

    HalfAdder_1B h1(a, b, w1, w2);
    HalfAdder_1B h2(w2, carry_in, w3, sum);
    or o1(carry_out, w1, w3);
    
endmodule

ALU/FullAdder_1B_t.v
//`include "FullAdder_1B.v"
module FullAdder_1B_t ();
    reg input_a, input_b, input_carry, output_carry, output_sum;
    reg[3:0] i;

    FullAdder_1B f(input_a, input_b, input_carry, output_carry, output_sum);

    task test(input A, input B, input carry);
        input_a = A;
        input_b = B;
        input_carry = carry;
        #100;
    endtask

    initial begin
        $dumpfile("FullAdder_1B.vcd");
        $dumpvars;

        for (i = 4'b0000; i < 4'b1000; i = i + 4'b0001) begin
            test(i[0], i[1], i[2]);
        end
        $finish;
    end
    
endmodule

ALU/FullAdder_1B.vcd
$date
	Tue Jul 13 20:28:29 2021
$end
$version
	Icarus Verilog
$end
$timescale
	1s
$end
$scope module FullAdder_1B_t $end
$var wire 1 ! output_sum $end
$var wire 1 " output_carry $end
$var reg 4 # i [3:0] $end
$var reg 1 $ input_a $end
$var reg 1 % input_b $end
$var reg 1 & input_carry $end
$scope module f $end
$var wire 1 $ a $end
$var wire 1 % b $end
$var wire 1 & carry_in $end
$var wire 1 " carry_out $end
$var wire 1 ' w3 $end
$var wire 1 ( w2 $end
$var wire 1 ) w1 $end
$var wire 1 ! sum $end
$scope module h1 $end
$var wire 1 $ a $end
$var wire 1 % b $end
$var wire 1 ) carry_out $end
$var wire 1 ( sum $end
$upscope $end
$scope module h2 $end
$var wire 1 ( a $end
$var wire 1 & b $end
$var wire 1 ' carry_out $end
$var wire 1 ! sum $end
$upscope $end
$upscope $end
$scope task test $end
$var reg 1 * A $end
$var reg 1 + B $end
$var reg 1 , carry $end
$upscope $end
$upscope $end
$enddefinitions $end
#0
$dumpvars
0,
0+
0*
0)
0(
0'
0&
0%
0$
b0 #
0"
0!
$end
#100
1!
1(
1$
1*
b1 #
#200
1%
0$
1+
0*
b10 #
#300
1"
0!
1)
0(
1$
1*
b11 #
#400
0"
1!
0)
1&
0%
0$
1,
0+
0*
b100 #
#500
1"
1'
0!
1(
1$
1*
b101 #
#600
1%
0$
1+
0*
b110 #
#700
0'
1!
1)
0(
1$
1*
b111 #
#800
b1000 #
